README.md
setup.py
weaverlet/__init__.py
weaverlet/base.py
weaverlet/logger.py
weaverlet.egg-info/PKG-INFO
weaverlet.egg-info/SOURCES.txt
weaverlet.egg-info/dependency_links.txt
weaverlet.egg-info/requires.txt
weaverlet.egg-info/top_level.txt
weaverlet/components/__init__.py
weaverlet/components/auth_router.py
weaverlet/components/div_signal.py
weaverlet/components/empty_layout.py
weaverlet/components/redirect.py
weaverlet/components/signal.py
weaverlet/components/simple_router.py
weaverlet/components/store.py