Metadata-Version: 2.1
Name: weaverlet
Version: 0.2.0
Summary: weaverlet
Home-page: UNKNOWN
Author: Alberto Garcia-Robledo
Author-email: alberto.garob@gmail.com
License: MIT
Platform: UNKNOWN
